{"cameraMode":{"drawMode":0,"name":"Shaded","section":"Shading Mode"},"sceneLighting":true,"audioPlay":false,"sceneViewState":{"m_AlwaysRefresh":false,"showFog":true,"showSkybox":true,"showFlares":true,"showImageEffects":true,"showParticleSystems":true,"showVisualEffectGraphs":true,"m_FxEnabled":true},"in2DMode":false,"pivot":{"x":-0.9717016220092773,"y":1.4778802394866944,"z":-1.7277958393096924},"rotation":{"x":0.01859799027442932,"y":0.9335730075836182,"z":-0.0490759052336216,"w":0.3552451431751251},"size":2.7497990131378176,"orthographic":false}